LICENSE
setup.py
tsc_base/__init__.py
tsc_base/async_func.py
tsc_base/cache.py
tsc_base/dependency.py
tsc_base/file_event_monitor.py
tsc_base/func.py
tsc_base/mp_basemodel.py
tsc_base/myclass.py
tsc_base/py_static_cfg.py
tsc_base/str_trie.py
tsc_base/web.py
tsc_base.egg-info/PKG-INFO
tsc_base.egg-info/SOURCES.txt
tsc_base.egg-info/dependency_links.txt
tsc_base.egg-info/requires.txt
tsc_base.egg-info/top_level.txt