Metadata-Version: 2.1
Name: tsc-base
Version: 0.58
Summary: 不依赖其他包的工具
Home-page: https://github.com/aitsc/tsc-base
Author: tanshicheng
License: GPLv3
Keywords: tools
Classifier: Intended Audience :: Developers
Classifier: License :: OSI Approved :: GNU General Public License v3 (GPLv3)
Classifier: Programming Language :: Python :: 3 :: Only
Classifier: Topic :: Software Development :: Libraries
Requires-Python: >=3.7
Provides-Extra: depend
License-File: LICENSE
